LICENSE
MANIFEST.in
README.md
setup.cfg
setup.py
mantis/__init__.py
mantis/__main__.py
mantis/app.py
mantis/command_line.py
mantis/config.py
mantis/cryptography.py
mantis/environment.py
mantis/helpers.py
mantis/managers.py
mantis/mantis.tpl
mantis/schema.py
mantis/commands/__init__.py
mantis/commands/compose.py
mantis/commands/configuration.py
mantis/commands/connection.py
mantis/commands/containers.py
mantis/commands/core.py
mantis/commands/django.py
mantis/commands/images.py
mantis/commands/nginx.py
mantis/commands/postgres.py
mantis/commands/secrets.py
mantis/commands/services.py
mantis/commands/volumes.py
mantis/extensions/__init__.py
mantis/extensions/django.py
mantis/extensions/nginx.py
mantis/extensions/postgres.py
mantis_cli.egg-info/PKG-INFO
mantis_cli.egg-info/SOURCES.txt
mantis_cli.egg-info/dependency_links.txt
mantis_cli.egg-info/entry_points.txt
mantis_cli.egg-info/requires.txt
mantis_cli.egg-info/top_level.txt
tests/__init__.py
tests/test_command_line.py
tests/test_config.py
tests/test_managers.py