Metadata-Version: 2.1
Name: mantis-cli
Version: 22.0.1
Summary: Management command to build and deploy webapps, especially based on Django
Home-page: https://github.com/PragmaticMates/mantis-cli
Author: Erik Telepovský
Author-email: info@pragmaticmates.com
Maintainer: Pragmatic Mates
Maintainer-email: info@pragmaticmates.com
License: GNU General Public License (GPL)
Keywords: management deployment docker command
Platform: UNKNOWN
Classifier: Programming Language :: Python
Classifier: Operating System :: OS Independent
Classifier: Environment :: Web Environment
Classifier: Intended Audience :: Developers
Classifier: Framework :: Django
Classifier: License :: OSI Approved :: GNU General Public License (GPL)
Classifier: Development Status :: 5 - Production/Stable
License-File: LICENSE
